[
    {
        "nombre": "casfsd",
        "apellido": "ds",
        "cargo": "s",
        "sueldob": ""
    },
    {
        "nombre": "",
        "apellido": "",
        "cargo": "",
        "sueldob": ""
    },
    {
        "nombre": "sdjkgnmds",
        "apellido": "gsdg",
        "cargo": "dsg",
        "sueldob": ""
    },
    {
        "nombre": "fgajsnfgaj",
        "apellido": "saf",
        "cargo": "as",
        "sueldob": "s"
    },
    {
        "nombre": "",
        "apellido": "",
        "cargo": "",
        "sueldob": ""
    }
]